MANIFEST.in
README.md
setup.cfg
setup.py
data/vipaccessUI.desktop
data/vipaccessUI.svg
vipaccessUI/__init__.py
vipaccessUI/main.py
vipaccessUI.egg-info/PKG-INFO
vipaccessUI.egg-info/SOURCES.txt
vipaccessUI.egg-info/dependency_links.txt
vipaccessUI.egg-info/entry_points.txt
vipaccessUI.egg-info/requires.txt
vipaccessUI.egg-info/top_level.txt