Metadata-Version: 1.0
Name: vipaccessUI
Version: 1.0.5
Summary: UNKNOWN
Home-page: https://github.com/chris17453/vipaccessUI/
Author: Charles Watkins
Author-email: charles@titandws.com
License: Creative Commons Attribution-Noncommercial-Share Alike license
Platform: UNKNOWN
